Metadata-Version: 1.1
Name: django-john-polls
Version: 0.1
Summary: A simple Django app to conduct Web-based polls.
Home-page: https://www.johnpeace.github.io/
Author: Ropo John Olatujoye
Author-email: princeolatjohnjoe@yahoo.com
License: BSD License
Platform: UNKNOWN
Classifier: Environment :: Web Environment
Classifier: Framework :: Django
Classifier: Framework :: Django :: 2.0
Classifier: Intended Audience :: Developers
Classifier: License :: OSI Approved :: BSD License
Classifier: Operating System :: OS Independent
Classifier: Programming Language :: Python
Classifier: Programming Language :: Python :: 3.5
Classifier: Programming Language :: Python :: 3.6
Classifier: Topic :: Internet :: WWW/HTTP
Classifier: Topic :: Internet :: WWW/HTTP :: Dynamic Content
